wbintegrator_office365/__init__.py
wbintegrator_office365/admin.py
wbintegrator_office365/apps.py
wbintegrator_office365/dynamic_preferences_registry.py
wbintegrator_office365/factories.py
wbintegrator_office365/filters.py
wbintegrator_office365/serializers.py
wbintegrator_office365/tasks.py
wbintegrator_office365/urls.py
wbintegrator_office365/configurations/__init__.py
wbintegrator_office365/configurations/configurations/__init__.py
wbintegrator_office365/importer/__init__.py
wbintegrator_office365/importer/api.py
wbintegrator_office365/importer/disable_signals.py
wbintegrator_office365/importer/parser.py
wbintegrator_office365/kpi_handlers/__init__.py
wbintegrator_office365/kpi_handlers/calls.py
wbintegrator_office365/migrations/0001_initial_squashed_squashed_0003_alter_calendar_owner_alter_calendarevent_organizer_and_more.py
wbintegrator_office365/migrations/0002_remove_calendar_owner_remove_calendarevent_activity_and_more.py
wbintegrator_office365/migrations/0003_alter_event_options.py
wbintegrator_office365/migrations/__init__.py
wbintegrator_office365/models/__init__.py
wbintegrator_office365/models/event.py
wbintegrator_office365/models/subscription.py
wbintegrator_office365/models/tenant.py
wbintegrator_office365/templates/admin/tenant_change_list.html
wbintegrator_office365/tests/__init__.py
wbintegrator_office365/tests/conftest.py
wbintegrator_office365/tests/test_admin.py
wbintegrator_office365/tests/test_models.py
wbintegrator_office365/tests/test_tasks.py
wbintegrator_office365/tests/test_views.py
wbintegrator_office365/tests/tests.py
wbintegrator_office365/viewsets/__init__.py
wbintegrator_office365/viewsets/display.py
wbintegrator_office365/viewsets/endpoints.py
wbintegrator_office365/viewsets/menu.py
wbintegrator_office365/viewsets/titles.py
wbintegrator_office365/viewsets/viewsets.py
wbintegrator_office365-2.2.6.dist-info/METADATA
wbintegrator_office365-2.2.6.dist-info/WHEEL
wbintegrator_office365-2.2.6.dist-info/RECORD
