Metadata-Version: 2.4
Name: wbintegrator_office365
Version: 2.2.6
Author-email: Christopher Wittlinger <c.wittlinger@stainly.com>
Requires-Dist: bs4==0.0.*
Requires-Dist: oauthlib==3.1.*
Requires-Dist: requests-oauthlib==1.3.*
Requires-Dist: wbcore
Requires-Dist: wbcrm
Requires-Dist: wbhuman-resources
